README.txt
setup.py
vsearch.py
custom_vsearch.egg-info/PKG-INFO
custom_vsearch.egg-info/SOURCES.txt
custom_vsearch.egg-info/dependency_links.txt
custom_vsearch.egg-info/top_level.txt