Metadata-Version: 2.1
Name: custom-vsearch
Version: 1.0
Summary: Search for specific letters into a given phrase.
Home-page: 
Author: Ariel Denaro
